mbclient/__init__.py
mbclient/cli.py
mbclient/experiment_emulator.py
mbclient/mbclient.py
mbclient/mbdatatypes.py
mbclient/mbplotter.py
mbclient/mimo_buffer_v1.py
mbclient-1.1.1.dist-info/LICENSE
mbclient-1.1.1.dist-info/METADATA
mbclient-1.1.1.dist-info/WHEEL
mbclient-1.1.1.dist-info/entry_points.txt
mbclient-1.1.1.dist-info/top_level.txt
mbclient-1.1.1.dist-info/RECORD
