Metadata-Version: 2.1
Name: mbclient
Version: 1.1.1
Summary: A client for the Moessbauer experiment of the KIT-Physics Laboratory course
Home-page: https://github.com/phylex/mbclient
Author: Alexander Becker
Author-email: galax.becker@live.de
License: GPL v3
Platform: UNKNOWN
Classifier: Development Status :: 5 - Production/Stable
Classifier: Environment :: Console
Classifier: Framework :: AsyncIO
Classifier: Intended Audience :: Science/Research
Classifier: License :: OSI Approved :: GNU General Public License v3 (GPLv3)
Classifier: Natural Language :: English
Classifier: Operating System :: POSIX :: Linux
Classifier: Programming Language :: Python :: 3.9
Classifier: Topic :: Education :: Computer Aided Instruction (CAI)
Classifier: Topic :: Scientific/Engineering :: Physics
Classifier: Topic :: Scientific/Engineering :: Visualization
Requires-Python: >=3.8
Requires-Dist: numpy
Requires-Dist: matplotlib
Requires-Dist: websockets
Requires-Dist: argparse
Requires-Dist: pyyaml
